drpt/__init__.py
drpt/__main__.py
drpt/drpt.py
drpt-0.8.2.dist-info/WHEEL
drpt-0.8.2.dist-info/LICENSE
drpt-0.8.2.dist-info/METADATA
drpt-0.8.2.dist-info/entry_points.txt
drpt-0.8.2.dist-info/RECORD
