Metadata-Version: 2.1
Name: drpt
Version: 0.8.2
Summary: Tool for preparing a dataset for publishing by dropping, renaming, scaling, and obfuscating columns defined in a recipe.
Home-page: https://github.com/ConX/drpt
License: BSD-3-Clause
Keywords: data,data science,preprocessing,scaling,obfuscation,data release,data publishing
Author: Constantinos Xanthopoulos
Author-email: conx@xanthopoulos.info
Requires-Python: >=3.9,<4.0
Classifier: Development Status :: 4 - Beta
Classifier: Intended Audience :: Science/Research
Classifier: License :: OSI Approved :: BSD License
Classifier: Operating System :: OS Independent
Classifier: Programming Language :: Python
Classifier: Programming Language :: Python :: 3
Classifier: Programming Language :: Python :: 3.9
Classifier: Programming Language :: Python :: 3.10
Classifier: Programming Language :: Python :: 3.11
Classifier: Programming Language :: Python :: 3
Classifier: Topic :: Scientific/Engineering
Requires-Dist: click (>=8.1.3,<9.0.0)
Requires-Dist: dask (>=2023.1.0,<2024.0.0)
Requires-Dist: jsonschema (>=4.17.3,<5.0.0)
Requires-Dist: pandas (>=1.5.2,<2.0.0)
Requires-Dist: pyarrow (>=10.0.1,<11.0.0)
Project-URL: Repository, https://github.com/ConX/drpt
